HongshanHuiChuangyeZhishiShouceV20Ban/README.md
HongshanHuiChuangyeZhishiShouceV20Ban/__init__.py
HongshanHuiChuangyeZhishiShouceV20Ban/__main__.py
HongshanHuiChuangyeZhishiShouceV20Ban/file.epub
HongshanHuiChuangyeZhishiShouceV20Ban/index.html
HongshanHuiChuangyeZhishiShouceV20Ban/css/__init__.py
HongshanHuiChuangyeZhishiShouceV20Ban/css/annotations.css
HongshanHuiChuangyeZhishiShouceV20Ban/css/main.css
HongshanHuiChuangyeZhishiShouceV20Ban/css/normalize.css
HongshanHuiChuangyeZhishiShouceV20Ban/css/popup.css
HongshanHuiChuangyeZhishiShouceV20Ban/font/__init__.py
HongshanHuiChuangyeZhishiShouceV20Ban/font/fontello.eot
HongshanHuiChuangyeZhishiShouceV20Ban/font/fontello.svg
HongshanHuiChuangyeZhishiShouceV20Ban/font/fontello.ttf
HongshanHuiChuangyeZhishiShouceV20Ban/font/fontello.woff
HongshanHuiChuangyeZhishiShouceV20Ban/img/__init__.py
HongshanHuiChuangyeZhishiShouceV20Ban/img/annotator-glyph-sprite.png
HongshanHuiChuangyeZhishiShouceV20Ban/img/annotator-icon-sprite.png
HongshanHuiChuangyeZhishiShouceV20Ban/img/apple-touch-icon.png
HongshanHuiChuangyeZhishiShouceV20Ban/img/cancelfullscreen.png
HongshanHuiChuangyeZhishiShouceV20Ban/img/close.png
HongshanHuiChuangyeZhishiShouceV20Ban/img/fullscreen.png
HongshanHuiChuangyeZhishiShouceV20Ban/img/loader.gif
HongshanHuiChuangyeZhishiShouceV20Ban/img/menu-icon.png
HongshanHuiChuangyeZhishiShouceV20Ban/img/save.png
HongshanHuiChuangyeZhishiShouceV20Ban/img/saved.png
HongshanHuiChuangyeZhishiShouceV20Ban/img/settings-s.png
HongshanHuiChuangyeZhishiShouceV20Ban/img/settings.png
HongshanHuiChuangyeZhishiShouceV20Ban/img/star.png
HongshanHuiChuangyeZhishiShouceV20Ban/js/__init__.py
HongshanHuiChuangyeZhishiShouceV20Ban/js/epub.js
HongshanHuiChuangyeZhishiShouceV20Ban/js/epub.min.js
HongshanHuiChuangyeZhishiShouceV20Ban/js/epub.min.map
HongshanHuiChuangyeZhishiShouceV20Ban/js/hooks.min.js
HongshanHuiChuangyeZhishiShouceV20Ban/js/hooks.min.map
HongshanHuiChuangyeZhishiShouceV20Ban/js/reader.js
hongshan_hui_chuangye_zhishi_shouce_v2_0_ban-2024.3.5.0.dist-info/METADATA
hongshan_hui_chuangye_zhishi_shouce_v2_0_ban-2024.3.5.0.dist-info/WHEEL
hongshan_hui_chuangye_zhishi_shouce_v2_0_ban-2024.3.5.0.dist-info/entry_points.txt
hongshan_hui_chuangye_zhishi_shouce_v2_0_ban-2024.3.5.0.dist-info/top_level.txt
hongshan_hui_chuangye_zhishi_shouce_v2_0_ban-2024.3.5.0.dist-info/RECORD
